message_flow/__init__.py
message_flow/message_email.py
message_flow/message_teams.py
message_flow/message_teams_chat.py
message_flow/message_whats.py
message_flow/report_pbi.py
message_flow/storage.py
ms_message_flow-0.0.4.dist-info/METADATA
ms_message_flow-0.0.4.dist-info/WHEEL
ms_message_flow-0.0.4.dist-info/top_level.txt
ms_message_flow-0.0.4.dist-info/RECORD
