Metadata-Version: 2.1
Name: ms-message-flow
Version: 0.0.4
Summary: Sistema de envio de mensagens
Home-page: https://dev.azure.com/brf-corp/Analytics-DataScience/_git/analytics-message-flow
Author: Cayo Slowik
Author-email: cayo.slowik@brf.com
License: UNKNOWN
Platform: UNKNOWN
Requires-Python: >=3.9
Requires-Dist: msal (==1.28.0)
Requires-Dist: requests (==2.31.0)
Requires-Dist: pymsteams (==0.2.2)
Requires-Dist: urllib3 (==2.2.1)
